mbus/__init__.py
mbus/mbus.py
mbus-0.0.1.dev1.dist-info/LICENSE.txt
mbus-0.0.1.dev1.dist-info/METADATA
mbus-0.0.1.dev1.dist-info/RECORD
mbus-0.0.1.dev1.dist-info/WHEEL
mbus-0.0.1.dev1.dist-info/top_level.txt
