Metadata-Version: 2.1
Name: mbus
Version: 0.0.1.dev1
Summary: A Python library for M-Bus
Home-page: https://github.com/pwitab/mbus
Author: Henrik Palmlund Wahlgren @ Palmlund Wahlgren Innovative Technology AB
Author-email: henrik@pwit.se
License: BSD-3-Clause
Platform: UNKNOWN
